{
  "name": "Dwarfs",
  "units": [
    {
      "name": "Warriors",
      "id": 0,
      "type": "Infantry",
      "points": 110,
      "attack": "3",
      "armor": "4+",
      "hits": 4,
      "size": 3,
      "min": 2
    },
    {
      "name": "Handgunners",
      "id": 1,
      "type": "Infantry",
      "points": 90,
      "attack": "3/1",
      "armor": "6+",
      "hits": 4,
      "size": 3,
      "range": "30cm"
    },
    {
      "name": "Rangers",
      "id": 2,
      "type": "Infantry",
      "points": 110,
      "attack": "3/1",
      "armor": "5+",
      "hits": 4,
      "size": 3,
      "range": "30cm",
      "max": 2
    },
    {
      "name": "Troll Slayers",
      "id": 3,
      "type": "Infantry",
      "points": 80,
      "attack": "5",
      "armor": "-",
      "hits": 4,
      "size": 3,
      "max": 2
    },
    {
      "name": "Cannon",
      "id": 4,
      "type": "Artillery",
      "points": 90,
      "attack": "1/2+bounce",
      "armor": "6+",
      "hits": 2,
      "size": 2,
      "range": "60cm",
      "max": 1
    },
    {
      "name": "Flame Cannon",
      "id": 5,
      "type": "Artillery",
      "points": 50,
      "attack": "1/2D6",
      "armor": "6+",
      "hits": 2,
      "size": 1,
      "range": "30cm",
      "max": 1
    },
    {
      "name": "Gyrocopter",
      "id": 6,
      "type": "Machine",
      "points": 75,
      "attack": "1/3",
      "armor": "5+",
      "hits": 3,
      "size": 1,
      "range": "30cm",
      "max": 1
    },
    {
      "name": "General",
      "id": 7,
      "type": "General",
      "points": 155,
      "attack": "+2",
      "size": 1,
      "command": 10,
      "armyMax": 1,
      "armyMin": 1
    },
    {
      "name": "Hero",
      "id": 8,
      "type": "Hero",
      "points": 80,
      "attack": "+1",
      "size": 1,
      "command": 8,
      "max": 1
    },
    {
      "name": "Runesmith",
      "id": 9,
      "type": "Hero",
      "points": 90,
      "attack": "+1",
      "size": 1,
      "command": 8,
      "max": 1,
      "upgradeRef": [0],
      "magicItemRef": [14, 15]
    }
  ],
  "upgrades": [
    {
      "id": 0,
      "name": "Anvil",
      "type": "Special",
      "attackModify": "+1",
      "pointsModify": 50,
      "armyMax": 1
    }
  ]
}